thought/__init__.py
thought/model_downloader.py
thought/model_loader.py
thought-0.1.4.dist-info/METADATA
thought-0.1.4.dist-info/WHEEL
thought-0.1.4.dist-info/RECORD
