Metadata-Version: 2.1
Name: thought
Version: 0.1.4
Summary: Thought is a light wrapper for llama cpp, the building block for implementing and managing an efficient LLM integration
Author: Andre van Zuydam
Author-email: andrevanzuydam@gmail.com
Requires-Python: >=3.9,<4.0
Classifier: Programming Language :: Python :: 3
Classifier: Programming Language :: Python :: 3.9
Classifier: Programming Language :: Python :: 3.10
Classifier: Programming Language :: Python :: 3.11
Classifier: Programming Language :: Python :: 3.12
Requires-Dist: gguf-modeldb (>=0.0.3,<0.0.4)
Requires-Dist: llama-cpp-python (==0.2.88)
